{
  "aegypti_version": "unknown",
  "conclusion": {
    "aegypti_fast_correct": 12330,
    "aegypti_fast_misses": 0,
    "aegypti_safe_correct": 12330,
    "aegypti_safe_misses": 0,
    "all_four_agree": 12330,
    "chiba_correct": 12330,
    "dense_instances": 5639,
    "dense_positives": 4799,
    "fallback_triggered": 840,
    "fast_dense_misses": 0,
    "instances": 12330,
    "invalid_witnesses": 0,
    "matmul_correct": 12330,
    "max_cover_ratio_complement": 1.2,
    "min_uncovered_on_positive": 3,
    "safe_all_correct": true,
    "scope_warning": "Finite evidence (exhaustive only up to n=7); not a worst-case completeness proof for the fast dense branch."
  },
  "elapsed_seconds": 31.535817861557007,
  "environment": {
    "networkx": "3.6.1",
    "numpy": "2.4.6",
    "platform": "Windows-11-10.0.26200-SP0",
    "python": "3.12.3",
    "scipy": "unknown"
  },
  "experiment": "car/ four-subject triangle comparison + dense-branch stress for Finlay",
  "fallback_parameter_available": true,
  "hvala_diagnostics_available": true,
  "omega_cap": 24,
  "oracle": "independent exact neighbourhood-intersection triangle test",
  "overall_summary": {
    "aegypti_fast_correct": 12330,
    "aegypti_fast_misses": 0,
    "aegypti_safe_correct": 12330,
    "aegypti_safe_misses": 0,
    "all_agree": 12330,
    "chiba_correct": 12330,
    "dense_branch_successes": 4799,
    "dense_instances": 5639,
    "dense_positives": 4799,
    "fallback_triggered": 840,
    "fast_dense_misses": 0,
    "instances": 12330,
    "invalid_witnesses": 0,
    "matmul_correct": 12330,
    "max_cover_ratio": 1.2,
    "mean_aegypti_fast_ms": 0.6301809733800382,
    "mean_aegypti_safe_ms": 0.6369829033635518,
    "mean_chiba_ms": 0.026177550521199588,
    "mean_matmul_ms": 0.1316743068127392,
    "min_uncovered_on_positive": 3,
    "truth_positive": 8860
  },
  "seed": 20260629,
  "subjects": {
    "aegypti_fast": "find_triangle_coordinates(G, fallback=False)",
    "aegypti_safe": "find_triangle_coordinates(G, fallback=True)",
    "chiba_nishizeki": "find_triangle_chiba_nishizeki(G)",
    "matrix_multiplication": "is_triangle_free_brute_force(A)"
  },
  "summary_by_family": {
    "atlas_exhaustive_n<=7": {
      "aegypti_fast_correct": 1244,
      "aegypti_fast_misses": 0,
      "aegypti_safe_correct": 1244,
      "aegypti_safe_misses": 0,
      "all_agree": 1244,
      "chiba_correct": 1244,
      "dense_branch_successes": 91,
      "dense_instances": 91,
      "dense_positives": 91,
      "fallback_triggered": 0,
      "fast_dense_misses": 0,
      "instances": 1244,
      "invalid_witnesses": 0,
      "matmul_correct": 1244,
      "max_cover_ratio": 1.0,
      "mean_aegypti_fast_ms": 0.020766479260410958,
      "mean_aegypti_safe_ms": 0.023021301660024925,
      "mean_chiba_ms": 0.007130868655818116,
      "mean_matmul_ms": 0.09982733060066795,
      "min_uncovered_on_positive": 3,
      "truth_positive": 1080
    },
    "er_dense": {
      "aegypti_fast_correct": 2500,
      "aegypti_fast_misses": 0,
      "aegypti_safe_correct": 2500,
      "aegypti_safe_misses": 0,
      "all_agree": 2500,
      "chiba_correct": 2500,
      "dense_branch_successes": 2425,
      "dense_instances": 2425,
      "dense_positives": 2425,
      "fallback_triggered": 0,
      "fast_dense_misses": 0,
      "instances": 2500,
      "invalid_witnesses": 0,
      "matmul_correct": 2500,
      "max_cover_ratio": 1.2,
      "mean_aegypti_fast_ms": 1.422010760055855,
      "mean_aegypti_safe_ms": 1.417215320165269,
      "mean_chiba_ms": 0.028393519506789745,
      "mean_matmul_ms": 0.17508932049386203,
      "min_uncovered_on_positive": 3,
      "truth_positive": 2500
    },
    "er_sparse": {
      "aegypti_fast_correct": 2486,
      "aegypti_fast_misses": 0,
      "aegypti_safe_correct": 2486,
      "aegypti_safe_misses": 0,
      "all_agree": 2486,
      "chiba_correct": 2486,
      "dense_branch_successes": 0,
      "dense_instances": 0,
      "dense_positives": 0,
      "fallback_triggered": 0,
      "fast_dense_misses": 0,
      "instances": 2486,
      "invalid_witnesses": 0,
      "matmul_correct": 2486,
      "max_cover_ratio": null,
      "mean_aegypti_fast_ms": 0.03598515762031911,
      "mean_aegypti_safe_ms": 0.03973451264225822,
      "mean_chiba_ms": 0.022820393748361128,
      "mean_matmul_ms": 0.11480764388679943,
      "min_uncovered_on_positive": null,
      "truth_positive": 1139
    },
    "near_turan": {
      "aegypti_fast_correct": 400,
      "aegypti_fast_misses": 0,
      "aegypti_safe_correct": 400,
      "aegypti_safe_misses": 0,
      "all_agree": 400,
      "chiba_correct": 400,
      "dense_branch_successes": 400,
      "dense_instances": 400,
      "dense_positives": 400,
      "fallback_triggered": 0,
      "fast_dense_misses": 0,
      "instances": 400,
      "invalid_witnesses": 0,
      "matmul_correct": 400,
      "max_cover_ratio": 1.0,
      "mean_aegypti_fast_ms": 1.70641225122381,
      "mean_aegypti_safe_ms": 1.6131040002801456,
      "mean_chiba_ms": 0.022780252329539508,
      "mean_matmul_ms": 0.1398015022277832,
      "min_uncovered_on_positive": 3,
      "truth_positive": 400
    },
    "omega3_tripartite": {
      "aegypti_fast_correct": 400,
      "aegypti_fast_misses": 0,
      "aegypti_safe_correct": 400,
      "aegypti_safe_misses": 0,
      "all_agree": 400,
      "chiba_correct": 400,
      "dense_branch_successes": 400,
      "dense_instances": 400,
      "dense_positives": 400,
      "fallback_triggered": 0,
      "fast_dense_misses": 0,
      "instances": 400,
      "invalid_witnesses": 0,
      "matmul_correct": 400,
      "max_cover_ratio": 1.0,
      "mean_aegypti_fast_ms": 0.6692550018487964,
      "mean_aegypti_safe_ms": 0.6437645011465065,
      "mean_chiba_ms": 0.017697250586934388,
      "mean_matmul_ms": 0.12993100099265575,
      "min_uncovered_on_positive": 3,
      "truth_positive": 400
    },
    "omega4_fourpartite": {
      "aegypti_fast_correct": 300,
      "aegypti_fast_misses": 0,
      "aegypti_safe_correct": 300,
      "aegypti_safe_misses": 0,
      "all_agree": 300,
      "chiba_correct": 300,
      "dense_branch_successes": 300,
      "dense_instances": 300,
      "dense_positives": 300,
      "fallback_triggered": 0,
      "fast_dense_misses": 0,
      "instances": 300,
      "invalid_witnesses": 0,
      "matmul_correct": 300,
      "max_cover_ratio": 1.0,
      "mean_aegypti_fast_ms": 0.657483667988951,
      "mean_aegypti_safe_ms": 0.6111516673505927,
      "mean_chiba_ms": 0.020183664358531434,
      "mean_matmul_ms": 0.1372823330651348,
      "min_uncovered_on_positive": 4,
      "truth_positive": 300
    },
    "planted_clique": {
      "aegypti_fast_correct": 1000,
      "aegypti_fast_misses": 0,
      "aegypti_safe_correct": 1000,
      "aegypti_safe_misses": 0,
      "all_agree": 1000,
      "chiba_correct": 1000,
      "dense_branch_successes": 987,
      "dense_instances": 987,
      "dense_positives": 987,
      "fallback_triggered": 0,
      "fast_dense_misses": 0,
      "instances": 1000,
      "invalid_witnesses": 0,
      "matmul_correct": 1000,
      "max_cover_ratio": 1.1666666666666667,
      "mean_aegypti_fast_ms": 1.3896994994720444,
      "mean_aegypti_safe_ms": 1.435013800219167,
      "mean_chiba_ms": 0.025082700070925057,
      "mean_matmul_ms": 0.15970580087741837,
      "min_uncovered_on_positive": 3,
      "truth_positive": 1000
    },
    "planted_triangle": {
      "aegypti_fast_correct": 1500,
      "aegypti_fast_misses": 0,
      "aegypti_safe_correct": 1500,
      "aegypti_safe_misses": 0,
      "all_agree": 1500,
      "chiba_correct": 1500,
      "dense_branch_successes": 0,
      "dense_instances": 0,
      "dense_positives": 0,
      "fallback_triggered": 0,
      "fast_dense_misses": 0,
      "instances": 1500,
      "invalid_witnesses": 0,
      "matmul_correct": 1500,
      "max_cover_ratio": null,
      "mean_aegypti_fast_ms": 0.034168532971913614,
      "mean_aegypti_safe_ms": 0.03728379941700647,
      "mean_chiba_ms": 0.020499600563198328,
      "mean_matmul_ms": 0.10961079989404728,
      "min_uncovered_on_positive": null,
      "truth_positive": 1500
    },
    "structured": {
      "aegypti_fast_correct": 1000,
      "aegypti_fast_misses": 0,
      "aegypti_safe_correct": 1000,
      "aegypti_safe_misses": 0,
      "all_agree": 1000,
      "chiba_correct": 1000,
      "dense_branch_successes": 196,
      "dense_instances": 365,
      "dense_positives": 196,
      "fallback_triggered": 169,
      "fast_dense_misses": 0,
      "instances": 1000,
      "invalid_witnesses": 0,
      "matmul_correct": 1000,
      "max_cover_ratio": 1.0,
      "mean_aegypti_fast_ms": 0.20256069977767766,
      "mean_aegypti_safe_ms": 0.21837219991721213,
      "mean_chiba_ms": 0.026660099043510854,
      "mean_matmul_ms": 0.11851679993560538,
      "min_uncovered_on_positive": 3,
      "truth_positive": 541
    },
    "tri_free_bipartite": {
      "aegypti_fast_correct": 1500,
      "aegypti_fast_misses": 0,
      "aegypti_safe_correct": 1500,
      "aegypti_safe_misses": 0,
      "all_agree": 1500,
      "chiba_correct": 1500,
      "dense_branch_successes": 0,
      "dense_instances": 671,
      "dense_positives": 0,
      "fallback_triggered": 671,
      "fast_dense_misses": 0,
      "instances": 1500,
      "invalid_witnesses": 0,
      "matmul_correct": 1500,
      "max_cover_ratio": 1.0,
      "mean_aegypti_fast_ms": 0.8725245995058989,
      "mean_aegypti_safe_ms": 0.9254252002186453,
      "mean_chiba_ms": 0.05429653283984711,
      "mean_matmul_ms": 0.12300493195652962,
      "min_uncovered_on_positive": null,
      "truth_positive": 0
    }
  },
  "summary_by_regime": {
    "dense": {
      "aegypti_fast_correct": 5639,
      "aegypti_fast_misses": 0,
      "aegypti_safe_correct": 5639,
      "aegypti_safe_misses": 0,
      "all_agree": 5639,
      "chiba_correct": 5639,
      "dense_branch_successes": 4799,
      "dense_instances": 5639,
      "dense_positives": 4799,
      "fallback_triggered": 840,
      "fast_dense_misses": 0,
      "instances": 5639,
      "invalid_witnesses": 0,
      "matmul_correct": 5639,
      "max_cover_ratio": 1.2,
      "mean_aegypti_fast_ms": 1.3420298459864017,
      "mean_aegypti_safe_ms": 1.3530100730471915,
      "mean_chiba_ms": 0.03438418131613337,
      "mean_matmul_ms": 0.15623557403958485,
      "min_uncovered_on_positive": 3,
      "truth_positive": 4799
    },
    "sparse": {
      "aegypti_fast_correct": 6691,
      "aegypti_fast_misses": 0,
      "aegypti_safe_correct": 6691,
      "aegypti_safe_misses": 0,
      "all_agree": 6691,
      "chiba_correct": 6691,
      "dense_branch_successes": 0,
      "dense_instances": 0,
      "dense_positives": 0,
      "fallback_triggered": 0,
      "fast_dense_misses": 0,
      "instances": 6691,
      "invalid_witnesses": 0,
      "matmul_correct": 6691,
      "max_cover_ratio": null,
      "mean_aegypti_fast_ms": 0.03025334034651794,
      "mean_aegypti_safe_ms": 0.0335339107098312,
      "mean_chiba_ms": 0.01926121648254594,
      "mean_matmul_ms": 0.11097471244834188,
      "min_uncovered_on_positive": null,
      "truth_positive": 4061
    }
  }
}